webpush/__init__.py
webpush/admin.py
webpush/apps.py
webpush/config.py
webpush/forms.py
webpush/jinja2.py
webpush/models.py
webpush/tests.py
webpush/urls.py
webpush/utils.py
webpush/views.py
webpush/migrations/0001_initial.py
webpush/migrations/0002_auto_20190603_0005.py
webpush/migrations/0003_subscriptioninfo_user_agent.py
webpush/migrations/0004_auto_20220831_1500.py
webpush/migrations/0005_auto_20230614_1529.py
webpush/migrations/__init__.py
webpush/static/webpush/new.json
webpush/static/webpush/webpush.js
webpush/static/webpush/webpush_serviceworker.js
webpush/templates/webpush.html
webpush/templates/webpush_button.html
webpush/templates/webpush_header.html
webpush/templates/webpush_serviceworker.js
webpush/templatetags/__init__.py
webpush/templatetags/webpush_notifications.py
django_webpush-0.3.6.dist-info/LICENSE
django_webpush-0.3.6.dist-info/METADATA
django_webpush-0.3.6.dist-info/WHEEL
django_webpush-0.3.6.dist-info/top_level.txt
django_webpush-0.3.6.dist-info/RECORD
