Metadata-Version: 2.1
Name: django-webpush
Version: 0.3.6
Summary: A simple Django package to integrate Web Push Notification in your Application
Home-page: https://www.github.com/safwanrahman/django-webpush
Author: Safwan Rahman
Author-email: safwan.rahman15@gmail.com
License: GNU Public License
Classifier: Environment :: Web Environment
Classifier: Framework :: Django
Classifier: Framework :: Django :: 1.8
Classifier: Intended Audience :: Developers
Classifier: License :: OSI Approved :: GNU General Public License v3 (GPLv3)
Classifier: Operating System :: OS Independent
Classifier: Programming Language :: Python
Classifier: Programming Language :: Python :: 2
Classifier: Programming Language :: Python :: 2.7
Classifier: Programming Language :: Python :: 3
Classifier: Topic :: Internet :: WWW/HTTP
Classifier: Topic :: Internet :: WWW/HTTP :: Dynamic Content
License-File: LICENSE
